usefulfunctions/__init__.py
usefulfunctions/__main__.py
usefulfunctions-0.0.2.dist-info/LICENSE
usefulfunctions-0.0.2.dist-info/METADATA
usefulfunctions-0.0.2.dist-info/WHEEL
usefulfunctions-0.0.2.dist-info/top_level.txt
usefulfunctions-0.0.2.dist-info/RECORD
