Metadata-Version: 2.1
Name: usefulfunctions
Version: 0.0.2
Summary: Some useful functions in python
Home-page: https://github.com/KazMalhotra/usefulfunctions
Author: Kaz Malhotra
Author-email: kazmal@protonmail.com
License: UNKNOWN
Platform: UNKNOWN
Classifier: Programming Language :: Python :: 3
Classifier: License :: OSI Approved :: MIT License
Classifier: Operating System :: OS Independent
Requires-Python: >=3.6
